housing_prediction_devaraj_saravana/__init__.py
housing_prediction_devaraj_saravana/ingest_data.py
housing_prediction_devaraj_saravana/score.py
housing_prediction_devaraj_saravana/train.py
housing_prediction_devaraj_saravana-0.0.1.dist-info/LICENSE
housing_prediction_devaraj_saravana-0.0.1.dist-info/METADATA
housing_prediction_devaraj_saravana-0.0.1.dist-info/WHEEL
housing_prediction_devaraj_saravana-0.0.1.dist-info/top_level.txt
housing_prediction_devaraj_saravana-0.0.1.dist-info/RECORD
