Metadata-Version: 2.1
Name: housing-prediction-devaraj-saravana
Version: 0.0.1
Summary: california's housing price prediction
Home-page: https://github.com/devaraj-saravana/mle-training
Author: Devaraj Saravanan
Author-email: "devaraj.saravana" <devaraj.saravana@tigeranalytics.com>
License: Copyright (c) 2018 The Python Packaging Authority        
Project-URL: Homepage, https://github.com/pypa/sampleproject
Project-URL: Bug Tracker, https://github.com/pypa/sampleproject/issues
Keywords: sample,example,setuptools
Classifier: Programming Language :: Python :: 3
Classifier: License :: OSI Approved :: MIT License
Classifier: Operating System :: OS Independent
Requires-Python: >=3.7
License-File: LICENSE
Requires-Dist: pandas
Requires-Dist: numpy
Requires-Dist: scipy
Requires-Dist: scikit-learn
Provides-Extra: test
Requires-Dist: pytest ; extra == 'test'
